pachca_client/__init__.py
pachca_client/api/__init__.py
pachca_client/api/button.py
pachca_client/api/cache.py
pachca_client/api/client.py
pachca_client/api/exceptions.py
pachca_client/api/file.py
pachca_client/api/pachca.py
pachca_client-0.2.0.dist-info/METADATA
pachca_client-0.2.0.dist-info/WHEEL
pachca_client-0.2.0.dist-info/top_level.txt
pachca_client-0.2.0.dist-info/RECORD
